{"cameraMode":{"drawMode":0,"name":"Shaded","section":"Shading Mode"},"sceneLighting":true,"audioPlay":false,"sceneViewState":{"showFog":true,"showMaterialUpdate":false,"showSkybox":true,"showFlares":true,"showImageEffects":true,"showParticleSystems":true,"showVisualEffectGraphs":true,"m_FxEnabled":true},"in2DMode":false,"pivot":{"x":-1.658576488494873,"y":2.9864513874053957,"z":4.037269592285156},"rotation":{"x":0.28231483697891238,"y":-0.3039153814315796,"z":0.0948110818862915,"w":0.9049553275108337},"size":3.375415563583374,"orthographic":false}